pygments_style_extras-0.0.3.dist-info/DESCRIPTION.rst
pygments_style_extras-0.0.3.dist-info/METADATA
pygments_style_extras-0.0.3.dist-info/RECORD
pygments_style_extras-0.0.3.dist-info/WHEEL
pygments_style_extras-0.0.3.dist-info/entry_points.txt
pygments_style_extras-0.0.3.dist-info/metadata.json
pygments_style_extras-0.0.3.dist-info/top_level.txt
styles/__init__.py
styles/github.py
styles/monokai_light.py
styles/railscasts.py
